odoo/addons/l10n_it_appointment_code/README.rst
odoo/addons/l10n_it_appointment_code/__init__.py
odoo/addons/l10n_it_appointment_code/__manifest__.py
odoo/addons/l10n_it_appointment_code/data/appointment_code_data.xml
odoo/addons/l10n_it_appointment_code/i18n/it.po
odoo/addons/l10n_it_appointment_code/i18n/l10n_it_appointment_code.pot
odoo/addons/l10n_it_appointment_code/models/__init__.py
odoo/addons/l10n_it_appointment_code/models/appointment_code.py
odoo/addons/l10n_it_appointment_code/readme/CONFIGURE.md
odoo/addons/l10n_it_appointment_code/readme/CONTRIBUTORS.md
odoo/addons/l10n_it_appointment_code/readme/DESCRIPTION.md
odoo/addons/l10n_it_appointment_code/readme/USAGE.md
odoo/addons/l10n_it_appointment_code/security/ir.model.access.csv
odoo/addons/l10n_it_appointment_code/static/description/icon.png
odoo/addons/l10n_it_appointment_code/static/description/index.html
odoo/addons/l10n_it_appointment_code/views/appointment_code_view.xml
odoo_addon_l10n_it_appointment_code-18.0.1.0.0.2.dist-info/METADATA
odoo_addon_l10n_it_appointment_code-18.0.1.0.0.2.dist-info/WHEEL
odoo_addon_l10n_it_appointment_code-18.0.1.0.0.2.dist-info/top_level.txt
odoo_addon_l10n_it_appointment_code-18.0.1.0.0.2.dist-info/RECORD
