Metadata-Version: 2.1
Name: odoo-addon-l10n_it_appointment_code
Version: 18.0.1.0.0.2
Requires-Python: >=3.10
Requires-Dist: odoo==18.0.*
Summary: Aggiunge la tabella dei codici carica da usare nelle dichiarazioni fiscali italiane
Home-page: https://github.com/OCA/l10n-italy
License: LGPL-3
Author: Openforce di Camilli Alessandro, Odoo Community Association (OCA)
Author-email: support@odoo-community.org
Classifier: Programming Language :: Python
Classifier: Framework :: Odoo
Classifier: Framework :: Odoo :: 18.0
Classifier: License :: OSI Approved :: GNU Lesser General Public License v3 (LGPLv3)
